disjoint_set/__init__.py
disjoint_set/main.py
disjoint_set/py.typed
disjoint_set/utils.py
disjoint_set-0.7.4.dist-info/LICENSE
disjoint_set-0.7.4.dist-info/METADATA
disjoint_set-0.7.4.dist-info/WHEEL
disjoint_set-0.7.4.dist-info/top_level.txt
disjoint_set-0.7.4.dist-info/RECORD
