Metadata-Version: 2.1
Name: disjoint-set
Version: 0.7.4
Summary: Disjoint set data structure implementation for Python
Home-page: https://github.com/mrapacz/disjoint_set
Maintainer: Maciej Rapacz
Maintainer-email: python.disjointset@gmail.com
Classifier: Programming Language :: Python :: 3
Classifier: License :: OSI Approved :: MIT License
Classifier: Operating System :: OS Independent
License-File: LICENSE
